[
  {
    "ticker": "AAON",
    "score": 40,
    "markdown": "# AAON: Data center efficiency beneficiary with thin execution evidence\n\n## Bear case first\n\nInsider selling is a decisive negative signal: net open-market sales of $24.4MM from 30 sales against only 4 buys over the trailing twelve months. Management describes a large data center TAM but provides no quantified targets, committed capex, or named customer programs. Customer evidence is thin – no named enterprise accounts, only two old federal awards totaling $129K, and just one other filer citing the company. Without design wins or capacity additions, the data center thesis remains speculative.\n\n## Business today\n\nAAON manufactures semi-custom HVAC equipment including rooftop units, air handlers, condensing units, and parts. Trailing twelve-month revenue was approximately $1,002MM; cash on hand as of 2025-12-31 was $13MM (SEC XBRL).\n\n## Chain position\n\nAAON sits as a supplier of cooling solutions (air handlers, liquid cooling) to data center operators and contractors. The economic logic: if data center electricity demand must be constrained to avoid grid upgrades, operators will invest in higher-efficiency cooling, raising adoption rates for AAON’s BASX product line.\n\n## Customer graph\n\nFederal awards total $129K from two Department of Defense contracts (W912CL12P0063, W91ZLK09P1276). No named enterprise customers appear in any excerpt. One other filer names AAON. Customer evidence is thin and concentrated in a small government segment.\n\n## Insider and management signal\n\nInsiders net sold $24.4MM open-market over the trailing twelve months – 30 sales versus 4 buys (Form 4). Management language from the June 2026 presentation cites a $43B data center construction market and a large TAM for BASX products [1][2][3], but lacks any specific customer commitments or capital allocation plans.\n\n## Street view\n\nNo sell-side analyst coverage or consensus target is reported in the available materials. The absence of coverage is consistent with a name that has a small data center revenue base relative to the market opportunity.\n\n## Non-linear case\n\nIf U.S. grid constraints or regulatory mandates force data center operators to lower PUE aggressively, AAON’s liquid cooling and high-efficiency air handlers could see adoption rates far above current levels. For this to become a multiple of today’s business, AAON would need to win contracts with multiple hyperscale operators and demonstrate that BASX revenue scales meaningfully above the current run rate. No evidence of such wins exists today.\n\n## Evidence\n\n- Data center buildout spending reached $43B in 2025 [1].  \n- Annual data center construction is expected at 8–12 GW, with a 240 GW pipeline [2].  \n- BASX’s addressable market is estimated relative to the products it provides to data centers [3].  \n\nDossier facts: insider net sales $24.4MM (Form 4); cash $13MM (SEC XBRL); federal awards $129K from DoD (USASpending); one other filer names AAON.\n\n## What would change our mind\n\n1. A named customer contract with a hyperscaler or colocation operator, disclosed in an 8-K.  \n2. Insider open-market buying of at least $1MM within a quarter (Form 4).  \n3. A material new federal award or increase in existing awards above $10MM (USASpending)."
  },
  {
    "ticker": "WS",
    "score": 32,
    "markdown": "# WS: Grid capex growth at historical average fails to accelerate electrical steel demand, leaving Worthington Steel overinvested with no near-term catalyst\n\n## Bear case first\nThe seed thesis assumes grid capex grows at a historical average, not a surge. That pace does not create incremental demand for electrical steel beyond baseline replacement. Worthington Steel’s capacity expansions in Canada, Mexico, and via the Sitem acquisition [2] may oversupply a tepid market. No insider has bought shares (Form 4). The single other filer naming the company provides no forward revenue signal. Thin customer evidence leaves the company reliant on auto demand, which is powertrain-agnostic [1] but cyclical.\n\n## Business today\nWorthington Steel sells flat-rolled steel products, with 80% of steel sold to the automotive market, including hybrid clutch plates and electrical steel laminations [1]. Revenue is $3093.3MM, cash $38.0MM (SEC XBRL). The company is expanding electrical steel capabilities and licensed ablation technology [2], but grid-related sales are not quantified.\n\n## Chain position\nThe company is a tier-one supplier of electrical steel to grid equipment manufacturers (transformers, motors) and automotive powertrain makers. Its economic logic depends on physical volume of steel consumed by downstream production. If grid utilities buy fewer transformers because capex is only average, electrical steel volumes flatten.\n\n## Customer graph\nNamed enterprise customers: none in excerpts. Federal awards: $0 (USASpending). One other filer names the company. Customer evidence is thin: no specific buyers, no contract awards, no government programs cited. The sole validation is an unnamed “other filer.”\n\n## Insider and management signal\nTrailing 12 months, net open-market insider activity is $0 across 0 buys and 0 sales by 0 insiders (Form 4). Management language is directional: “well-positioned to capitalize on opportunities” and lists expansion actions [0][2], but provides no quantified targets, named customer programs, or committed spending milestones.\n\n## Street view\nSell-side coverage is absent: unknown analysts, consensus n/a, mean target n/a. The lack of any published rating or price target makes the stock a neglected name; no bank reports are available to confirm or contest the bear case.\n\n## Non-linear case\nIf data center load growth overwhelms grid capacity despite efficiency gains, regulators could force accelerated transmission and substation buildout. That would spike transformer orders and electrical steel demand. For Worthington to benefit, it must win named contracts; the current filings show no such pipeline. Execution would require the licensing and acquired capacity to be fully utilized, a scenario unsupported by any filing evidence.\n\n## Evidence\n- Management states it is “well-positioned to capitalize on opportunities from expected growth in electricity usage to support data center growth and vehicle electrification combined with the modernization and expansion of the electric grid” [0].\n- 80% of steel sold to automotive market; includes hybrid clutch plate and electrical steel laminations [1].\n- Expanding electrical steel capabilities in Canada and Mexico; licensed ablation technology; Sitem acquisition strengthens global presence for electrical steel [2].\n- Deferred tax asset adjustment related to Tempel’s electrical steel facility in Nagold, Germany, part of Sitem acquisition consideration [3].\n\n## What would change our mind\n- A Form 4 filing showing insider open-market purchases of $100K+ within a quarter (Form 4).\n- A named customer award (e.g., a utility or OEM contract) disclosed in an 8-K or 10-K.\n- A fiscal-year guidance update in an 8-K or earnings release that includes a quantified electrical steel revenue growth target."
  },
  {
    "ticker": "AROC",
    "score": 20,
    "markdown": "# AROC: US grid capex grows at a historical average pace through 2030 as data center electricity demand is largely offset by efficiency gains and on-site generation.\n## Bear case first\nArchrock fails to capture any data center-related growth because the filings show no connection to that end market. The only data center reference is a director’s independent role at Powell Industries [0]; Archrock’s own business is limited to natural gas compression for the energy industry [1][2]. Insider trading is flat over the trailing 12 months (Form 4), and management language never mentions data centers or on-site generation. Customer evidence is thin, a single $68M federal award from the Department of the Interior (USASpending), and no enterprise customer names exist. Without customer adoption, pipeline contracts, or capital commitments, the thesis that on-site gas generation drives incremental compression demand for Archrock remains unsupported.\n\n## Business today\nArchrock is a natural gas compression services provider to U.S. energy industry customers and a supplier of aftermarket services for compression equipment [1][2]. Revenue was $1,489.8MM and cash was $1.6MM as of 2025-12-31 (SEC XBRL).\n\n## Chain position\nThe thesis positions Archrock as an on-site gas supply infrastructure provider (order 2 beneficiary). The economic logic: data centers installing gas-fired fuel cells or microturbines need dedicated pipeline laterals and compression, which should increase demand for Archrock’s midstream compression services. No filing evidence confirms this logic has materialized for Archrock.\n\n## Customer graph\nGovernment: $68M in federal awards from the Department of the Interior (USASpending). Enterprise: zero named customers in any excerpt. Unproven: no other filers name Archrock. Customer graph is extremely thin.\n\n## Insider and management signal\nOver the trailing 12 months, insider net open-market activity was $0 across 0 buys and 0 sales by 0 insiders (Form 4). Management language in the sole 8-K excerpt focuses on generic compression services and makes no mention of data centers, on-site generation, or any strategic pivot toward that market [1][2].\n\n## Street view\nSell-side coverage is unknown. Analyst count, consensus, and mean target are all n/a. The stock is effectively uncovered, which is itself a risk for a thesis requiring near-term catalysts.\n\n## Non-linear case\nA multiple of today’s business would require Archrock to capture a meaningful share of data center gas infrastructure contracts. This path needs observable evidence: design wins for pipeline laterals serving data centers, a capital spending program targeting data center customers, or management explicitly allocating resources to on-site generation. None of these appear in the filings.\n\n## Evidence\n- [0] Singh serves as an independent director of Powell Industries, a power solutions provider serving data centers among other markets.\n- [1] Archrock describes itself as an energy infrastructure company focused on midstream natural gas compression.\n- [2] Archrock states it is a premier provider of natural gas compression services to the U.S. energy industry.\n\n## What would change our mind\n1. A customer contract or press release naming a data center operator or developer as a client (8-K or 10-K).\n2. Insider open-market buying of at least $100K in a single transaction (Form 4).\n3. Management commentary in an earnings transcript that sets a revenue target or capital commitment for data center-related compression services (8-K or 10-Q exhibit)."
  },
  {
    "ticker": "NWE",
    "score": 20,
    "markdown": "# NWE: Grid reliability focus leaves no exposure to renewable interconnection opportunity, with zero near-term catalysts or insider conviction\n\n## Bear case first\nThe only project cited strengthens grid reliability, not renewable interconnection, with a 2032 in-service date offering no near-term catalyst [1]. Filing evidence contains no mention of renewable development, transmission expansion, or any mechanism that would benefit from faster interconnection queues. Insider activity is flat (Form 4), and the customer base is concentrated on two federal awards from the Department of Health and Human Services totaling $209M, introducing dependency risk. Management language is generic expense efficiency and debt/cap targets [0], no strategic pivot toward the seed theme.\n\n## Business today\nNorthWestern Energy provides regulated electric and gas utility services. Revenue was $414.3MM and cash $8.8MM as of December 31, 2025 (SEC XBRL). The company emphasizes electric expense efficiency relative to regional peers [0].\n\n## Chain position\nNWE occupies the regulated utility node (grid reliability), not the utility-scale renewable developer node. The project in evidence [1] reinforces existing grid performance but does not enable new renewable interconnection, removing it from the adoption chain for renewable transmission.\n\n## Customer graph\nGovernment customers account for $209M in federal awards: Department of Health and Human Services ($172M award 75H70924P00110 and $37M award 75H70925P00009) (USASpending). No named enterprise customers appear in excerpts; two other filers name the company. Customer evidence is thin and concentrated on a single agency.\n\n## Insider and management signal\nNo open-market insider buying or selling over the trailing 12 months (Form 4). Management language in [0] is limited to debt/capital ratio targets (50–55%) and disciplined expense programs; no quantified targets or named programs related to renewable transmission appear.\n\n## Street view\nSell-side coverage is unknown; analyst count, consensus, and mean target are not available. The absence of coverage reinforces the lack of catalyst and low investor attention for this name.\n\n## Non-linear case\nFor a multiple, NWE would need to pivot into large-scale transmission that specifically interconnects utility-scale renewables, or become a developer itself. That requires a strategic shift not present in filings. The 2032 reliability project could theoretically be expanded, but no evidence supports that. Alternatively, HHS awards could scale dramatically, but that is unrelated to the grid capex theme.\n\n## Evidence\n- [0] (8-K, filed 2026-06-02): Target 50–55% debt/cap ratio; expense efficiency program ranking favorably among peers.\n- [1] (8-K, filed 2026-06-02): Grid reliability project targeting 2032 in-service date.\n\n## What would change our mind\n1. An 8-K or 10-Q announcing a transmission project explicitly linked to renewable interconnection or queue reduction.  \n2. Open-market insider purchases on a Form 4.  \n3. A federal award (USASpending) related to transmission or renewable energy infrastructure."
  },
  {
    "ticker": "AMR",
    "score": 18,
    "markdown": "# AMR: Grid capex thesis does not apply to a pure-play coal miner with no exposure to copper or aluminum demand\n\n## Bear case first\nThe seed thesis posits that US grid capex growth will be offset by efficiency, reducing copper and aluminum demand and thus mining equipment orders. AMR is a coal miner, not a copper or aluminum miner, and not an equipment manufacturer. Its revenue derives entirely from coal sales [0][1][5]; no filing evidence mentions copper, aluminum, data centers, or grid-related demand. Insider buying is strong ($30.3MM net) but uncorrelated to the theme. The customer graph shows zero named enterprise customers and zero federal awards, leaving concentration risk unaddressed.\n\n## Business today\nAMR produces metallurgical and thermal coal for steelmaking, coke plants, and electricity generation [0][5]. Revenue was $2,122.6MM and cash holdings $366.0MM as of December 31, 2025 (SEC XBRL). The company operates surface and underground mines and sources mining equipment, parts, and consumables from suppliers [2][3].\n\n## Chain position\nAMR is a coal producer, not a mining equipment manufacturer. It sits at the consuming end of the equipment supply chain, purchasing trucks, shovels, and parts for its own operations [2][3]. The seed thesis expects reduced equipment orders from copper miners, but AMR’s own equipment demand is driven by coal markets, not copper.\n\n## Customer graph\nNo named enterprise customers appear in the filings. Federal award dollars are $0 (USASpending). Three other filers name AMR, but their identity is not disclosed. All customer evidence is unproven; the company’s end-market is commodity coal sold to utilities and steelmakers, but specific counterparties are absent from the excerpts.\n\n## Insider and management signal\nTrailing 12-month Form 4 filings show net open-market insider purchases of $30.3MM across 68 buys and 11 sales by three insiders, indicating strong insider conviction in the equity. Management language in the 10-K focuses on coal market risks, regulatory compliance, and equipment supply reliability [4][5][6][9][12][13]; there is no mention of data centers, grid capex, or copper-aluminum demand.\n\n## Street view\nNo sell-side analyst ratings, consensus estimates, or mean targets are reported in the dossier. Coverage is effectively absent, consistent with a small-cap miner outside the theme’s focus.\n\n## Non-linear case\nA non-linear outcome would require a fundamental transformation: AMR pivoting to mine copper or other grid-critical metals, or data center operators directly contracting for coal-fired power to meet reliability needs. Neither is supported by any filing evidence. The business remains a pure coal producer; without a catalyst linking it to the theme, the path to a multiple of current value is speculative.\n\n## Evidence\n- The company’s business is coal mining with a preferred method of mining determined [0].\n- Contour mining uses surface machinery to follow coal seams [1].\n- Principal goods include mining equipment, parts, and consumables [2].\n- AMR purchased a mining equipment component business to secure parts supply [3].\n- Operations are subject to Surface Mining Control and Reclamation Act regulations [4][11][15].\n- End use of coal generates GHGs; mining equipment combustion also emits GHGs [5][8].\n- Efficiency gains and conservation reduce electricity consumption, harming coal demand [6][9].\n- Blasting activities are regulated [7].\n- Competition for skilled miners affects operating efficiency [10].\n- Reliable supply of mining equipment and materials is critical; shortages harm operations [12][13].\n- Liquid trading markets reduce price volatility [14].\n- Asset retirement obligations arise from reclamation laws [15].\n- Mining equipment is referenced in a table of contents [16].\n\n## What would change our mind\n1. A Form 4 showing net insider selling or a sharp reversal of the buying trend.\n2. A 10-K or 8-K that discloses a significant new business segment tied to copper, aluminum, or data center infrastructure.\n3. A federal award (USASpending) or named customer contract explicitly linking AMR to grid-related metal supply."
  }
]